[{"created":"20220316131546254","text":"","title":"1 WARNUNG STEMPEL (gelb)","modified":"20220324173421438","tags":"$:/tags/TextEditor/Snippet STEMPEL","type":"text/vnd.tiddlywiki","bag":"default","caption":"1 &#128065; WARNUNG STEMPEL (gelb)","revision":"3"},{"created":"20220316123939018","text":"<p style=\"display: flex; align-items:center; width: 75%; opacity: .7; padding: 5px; border: 2px solid Gold; margin: 0; background-color: #fcf8e3; color: black; border-radius: 25px;\"><div style=\"font-size: 125%\">&#128065;</div>&nbsp;&nbsp;","title":"1 WARNUNG STEMPEL (gelb)/prefix","modified":"20220324173407190","tags":"STEMPEL","type":"text/vnd.tiddlywiki","bag":"default","revision":"2"},{"created":"20220316125826681","text":"</p>","title":"1 WARNUNG STEMPEL (gelb)/suffix","modified":"20220322142755052","tags":"STEMPEL","type":"text/vnd.tiddlywiki","bag":"default","revision":"1"},{"created":"20220316131546254","text":"","title":"2 DANGER STEMPEL (rot)","modified":"20220324173520927","tags":"$:/tags/TextEditor/Snippet STEMPEL","type":"text/vnd.tiddlywiki","bag":"default","caption":"2 &#9888; DANGER STEMPEL (rot)","revision":"2"},{"created":"20220316123939018","text":"<p style=\"display: flex; align-items:center; width: 75%; opacity: .7; padding: 5px; border: 2px solid Red; margin: 0; background-color: #f2dede; color: black; border-radius: 25px;\"><div style=\"font-size: 125%\">&#9888;</div>&nbsp;&nbsp;","title":"2 DANGER STEMPEL (rot)/prefix","modified":"20220324173539615","tags":"STEMPEL","type":"text/vnd.tiddlywiki","bag":"default","revision":"2"},{"created":"20220316125826681","text":"</p>","title":"2 DANGER STEMPEL (rot)/suffix","modified":"20220322142733372","tags":"STEMPEL","type":"text/vnd.tiddlywiki","bag":"default","revision":"1"},{"created":"20220316131546254","text":"","title":"3 ERFOLGREICH STEMPEL (gruen)","modified":"20220324173613335","tags":"$:/tags/TextEditor/Snippet STEMPEL","type":"text/vnd.tiddlywiki","bag":"default","caption":"3 &#10003; ERFOLGREICH STEMPEL (gruen)","revision":"2"},{"created":"20220316123939018","text":"<p style=\"display: flex; align-items:center; width: 75%; opacity: .7; padding: 5px; border: 2px solid Green; margin: 0; background-color: #dff0d8; color: black; border-radius: 25px;\"><div style=\"font-size: 125%\">&#10003;</div>&nbsp;&nbsp;","title":"3 ERFOLGREICH STEMPEL (gruen)/prefix","modified":"20220324173628775","tags":"STEMPEL","type":"text/vnd.tiddlywiki","bag":"default","revision":"2"},{"created":"20220316125826681","text":"</p>","title":"3 ERFOLGREICH STEMPEL (gruen)/suffix","modified":"20220322142745901","tags":"STEMPEL","type":"text/vnd.tiddlywiki","bag":"default","revision":"1"},{"created":"20220316131546254","text":"","title":"4 INFO STEMPEL (blau)","modified":"20220324173701623","tags":"$:/tags/TextEditor/Snippet STEMPEL","type":"text/vnd.tiddlywiki","bag":"default","caption":"4 &#128712; INFO STEMPEL (blau)","revision":"2"},{"created":"20220316123939018","text":"<p style=\"display: flex; width: 75%; opacity: .7; padding: 5px; border: 2px solid #1eb0f8; margin: 0; background-color: #d9edf7; color: black; border-radius: 25px;\"><div style=\"font-size: 125%\">&#128712;</div>&nbsp;&nbsp;","title":"4 INFO STEMPEL (blau)/prefix","modified":"20220324173715576","tags":"STEMPEL","type":"text/vnd.tiddlywiki","bag":"default","revision":"2"},{"created":"20220316125826681","text":"</p>","title":"4 INFO STEMPEL (blau)/suffix","modified":"20220322142707269","tags":"STEMPEL","type":"text/vnd.tiddlywiki","bag":"default","revision":"1"},{"created":"20220316160148135","text":"| |Alpha |Beta |Gamma |Delta |\n|:-|:-:|:-:|:-:|:-:|\n|Beta | | | | |\n|Gamma | | | | |\n|Delta | | | | |\n| |a|b|c|d|","tags":"$:/tags/TextEditor/Snippet STEMPEL","title":"5 MARKDOWN Tabelle mit 5 Spalten, 4 Zeilen, Kopf- und Fußzeile","modified":"20220325120323181","type":"text/x-markdown","bag":"default","caption":"5 MARKDOWN Tabelle mit 5 Spalten, 4 Zeilen, Kopf- und Fußzeile","revision":"2"}]